{
    "Black footed Albatross": "Phoebastria nigripes",
    "Laysan Albatross": "Phoebastria immutabilis",
    "Sooty Albatross": "Phoebetria fusca",
    "Groove billed Ani": "Crotophaga sulcirostris",
    "Crested Auklet": "Aethia cristatella",
    "Least Auklet": "Aethia pusilla",
    "Parakeet Auklet": "Aethia psittacula",
    "Rhinoceros Auklet": "Cerorhinca monocerata",
    "Brewer Blackbird": "Euphagus cyanocephalus",
    "Red winged Blackbird": "Agelaius phoeniceus",
    "Rusty Blackbird": "Euphagus carolinus",
    "Yellow headed Blackbird": "Xanthocephalus xanthocephalus",
    "Bobolink": "Dolichonyx oryzivorus",
    "Indigo Bunting": "Passerina cyanea",
    "Lazuli Bunting": "Passerina amoena",
    "Painted Bunting": "Passerina ciris",
    "Cardinal": "Cardinalis cardinalis",
    "Spotted Catbird": "Ailuroedus maculosus",
    "Gray Catbird": "Dumetella carolinensis",
    "Yellow breasted Chat": "Icteria virens",
    "Eastern Towhee": "Pipilo erythrophthalmus",
    "Chuck will Widow": "Antrostomus carolinensis",
    "Brandt Cormorant": "Urile penicillatus",
    "Red faced Cormorant": "Urile urile",
    "Pelagic Cormorant": "Urile pelagicus",
    "Bronzed Cowbird": "Molothrus aeneus",
    "Shiny Cowbird": "Molothrus bonariensis",
    "Brown Creeper": "Certhia americana",
    "American Crow": "Corvus brachyrhynchos",
    "Fish Crow": "Corvus ossifragus",
    "Black billed Cuckoo": "Coccyzus erythropthalmus",
    "Mangrove Cuckoo": "Coccyzus minor",
    "Yellow billed Cuckoo": "Coccyzus americanus",
    "Gray crowned Rosy Finch": "Leucosticte tephrocotis",
    "Purple Finch": "Haemorhous purpureus",
    "Northern Flicker": "Colaptes auratus",
    "Acadian Flycatcher": "Empidonax virescens",
    "Great Crested Flycatcher": "Myiarchus crinitus",
    "Least Flycatcher": "Empidonax minimus",
    "Olive sided Flycatcher": "Contopus cooperi",
    "Scissor tailed Flycatcher": "Tyrannus forficatus",
    "Vermilion Flycatcher": "Pyrocephalus rubinus",
    "Yellow bellied Flycatcher": "Empidonax flaviventris",
    "Frigatebird": "Fregata magnificens",
    "Northern Fulmar": "Fulmarus glacialis",
    "Gadwall": "Mareca strepera",
    "American Goldfinch": "Spinus tristis",
    "European Goldfinch": "Carduelis carduelis",
    "Boat tailed Grackle": "Quiscalus major",
    "Eared Grebe": "Podiceps nigricollis",
    "Horned Grebe": "Podiceps auritus",
    "Pied billed Grebe": "Podilymbus podiceps",
    "Western Grebe": "Aechmophorus occidentalis",
    "Blue Grosbeak": "Passerina caerulea",
    "Evening Grosbeak": "Hesperiphona vespertina",
    "Pine Grosbeak": "Pinicola enucleator",
    "Rose breasted Grosbeak": "Pheucticus ludovicianus",
    "Pigeon Guillemot": "Cepphus columba",
    "California Gull": "Larus californicus",
    "Glaucous winged Gull": "Larus glaucescens",
    "Heermann Gull": "Larus heermanni",
    "Herring Gull": "Larus argentatus",
    "Ivory Gull": "Pagophila eburnea",
    "Ring billed Gull": "Larus delawarensis",
    "Slaty backed Gull": "Larus schistisagus",
    "Western Gull": "Larus occidentalis",
    "Anna Hummingbird": "Calypte anna",
    "Ruby throated Hummingbird": "Archilochus colubris",
    "Rufous Hummingbird": "Selasphorus rufus",
    "Green Violetear": "Colibri thalassinus",
    "Long tailed Jaeger": "Stercorarius longicaudus",
    "Pomarine Jaeger": "Stercorarius pomarinus",
    "Blue Jay": "Cyanocitta cristata",
    "Florida Jay": "Aphelocoma coerulescens",
    "Green Jay": "Cyanocorax yncas",
    "Dark eyed Junco": "Junco hyemalis",
    "Tropical Kingbird": "Tyrannus melancholicus",
    "Gray Kingbird": "Tyrannus dominicensis",
    "Belted Kingfisher": "Megaceryle alcyon",
    "Green Kingfisher": "Chloroceryle americana",
    "Pied Kingfisher": "Ceryle rudis",
    "Ringed Kingfisher": "Megaceryle torquata",
    "White breasted Kingfisher": "Halcyon smyrnensis",
    "Red legged Kittiwake": "Rissa brevirostris",
    "Horned Lark": "Eremophila alpestris",
    "Pacific Loon": "Gavia pacifica",
    "Mallard": "Anas platyrhynchos",
    "Western Meadowlark": "Sturnella neglecta",
    "Hooded Merganser": "Lophodytes cucullatus",
    "Red breasted Merganser": "Mergus serrator",
    "Mockingbird": "Mimus polyglottos",
    "Nighthawk": "Chordeiles minor",
    "Clark Nutcracker": "Nucifraga columbiana",
    "White breasted Nuthatch": "Sitta carolinensis",
    "Baltimore Oriole": "Icterus galbula",
    "Hooded Oriole": "Icterus cucullatus",
    "Orchard Oriole": "Icterus spurius",
    "Scott Oriole": "Icterus parisorum",
    "Ovenbird": "Seiurus aurocapilla",
    "Brown Pelican": "Pelecanus occidentalis",
    "White Pelican": "Pelecanus erythrorhynchos",
    "Western Wood Pewee": "Contopus sordidulus",
    "Sayornis": "Sayornis phoebe",
    "American Pipit": "Anthus rubescens",
    "Whip poor Will": "Antrostomus vociferus",
    "Horned Puffin": "Fratercula corniculata",
    "Common Raven": "Corvus corax",
    "White necked Raven": "Corvus albicollis",
    "American Redstart": "Setophaga ruticilla",
    "Geococcyx": "Geococcyx californianus",
    "Loggerhead Shrike": "Lanius ludovicianus",
    "Great Grey Shrike": "Lanius excubitor",
    "Baird Sparrow": "Centronyx bairdii",
    "Black throated Sparrow": "Amphispiza bilineata",
    "Brewer Sparrow": "Spizella breweri",
    "Chipping Sparrow": "Spizella passerina",
    "Clay colored Sparrow": "Spizella pallida",
    "House Sparrow": "Passer domesticus",
    "Field Sparrow": "Spizella pusilla",
    "Fox Sparrow": "Passerella iliaca",
    "Grasshopper Sparrow": "Ammodramus savannarum",
    "Harris Sparrow": "Zonotrichia querula",
    "Henslow Sparrow": "Centronyx henslowii",
    "Le Conte Sparrow": "Ammospiza leconteii",
    "Lincoln Sparrow": "Melospiza lincolnii",
    "Nelson Sharp tailed Sparrow": "Ammospiza nelsoni",
    "Savannah Sparrow": "Passerculus sandwichensis",
    "Seaside Sparrow": "Ammospiza maritima",
    "Song Sparrow": "Melospiza melodia",
    "Tree Sparrow": "Spizelloides arborea",
    "Vesper Sparrow": "Pooecetes gramineus",
    "White crowned Sparrow": "Zonotrichia leucophrys",
    "White throated Sparrow": "Zonotrichia albicollis",
    "Cape Glossy Starling": "Lamprotornis nitens",
    "Bank Swallow": "Riparia riparia",
    "Barn Swallow": "Hirundo rustica",
    "Cliff Swallow": "Petrochelidon pyrrhonota",
    "Tree Swallow": "Tachycineta bicolor",
    "Scarlet Tanager": "Piranga olivacea",
    "Summer Tanager": "Piranga rubra",
    "Artic Tern": "Sterna paradisaea",
    "Black Tern": "Chlidonias niger",
    "Caspian Tern": "Hydroprogne caspia",
    "Common Tern": "Sterna hirundo",
    "Elegant Tern": "Thalasseus elegans",
    "Forsters Tern": "Sterna forsteri",
    "Least Tern": "Sternula antillarum",
    "Green tailed Towhee": "Pipilo chlorurus",
    "Brown Thrasher": "Toxostoma rufum",
    "Sage Thrasher": "Oreoscoptes montanus",
    "Black capped Vireo": "Vireo atricapilla",
    "Blue headed Vireo": "Vireo solitarius",
    "Philadelphia Vireo": "Vireo philadelphicus",
    "Red eyed Vireo": "Vireo olivaceus",
    "Warbling Vireo": "Vireo gilvus",
    "White eyed Vireo": "Vireo griseus",
    "Yellow throated Vireo": "Vireo flavifrons",
    "Bay breasted Warbler": "Setophaga castanea",
    "Black and white Warbler": "Mniotilta varia",
    "Black throated Blue Warbler": "Setophaga caerulescens",
    "Blue winged Warbler": "Vermivora cyanoptera",
    "Canada Warbler": "Cardellina canadensis",
    "Cape May Warbler": "Setophaga tigrina",
    "Cerulean Warbler": "Setophaga cerulea",
    "Chestnut sided Warbler": "Setophaga pensylvanica",
    "Golden winged Warbler": "Vermivora chrysoptera",
    "Hooded Warbler": "Setophaga citrina",
    "Kentucky Warbler": "Geothlypis formosa",
    "Magnolia Warbler": "Setophaga magnolia",
    "Mourning Warbler": "Geothlypis philadelphia",
    "Myrtle Warbler": "Setophaga coronata",
    "Nashville Warbler": "Leiothlypis ruficapilla",
    "Orange crowned Warbler": "Leiothlypis celata",
    "Palm Warbler": "Setophaga palmarum",
    "Pine Warbler": "Setophaga pinus",
    "Prairie Warbler": "Setophaga discolor",
    "Prothonotary Warbler": "Protonotaria citrea",
    "Swainson Warbler": "Limnothlypis swainsonii",
    "Tennessee Warbler": "Leiothlypis peregrina",
    "Wilson Warbler": "Cardellina pusilla",
    "Worm eating Warbler": "Helmitheros vermivorum",
    "Yellow Warbler": "Setophaga petechia",
    "Northern Waterthrush": "Parkesia noveboracensis",
    "Louisiana Waterthrush": "Parkesia motacilla",
    "Bohemian Waxwing": "Bombycilla garrulus",
    "Cedar Waxwing": "Bombycilla cedrorum",
    "American Three toed Woodpecker": "Picoides dorsalis",
    "Pileated Woodpecker": "Dryocopus pileatus",
    "Red bellied Woodpecker": "Melanerpes carolinus",
    "Red cockaded Woodpecker": "Leuconotopicus borealis",
    "Red headed Woodpecker": "Melanerpes erythrocephalus",
    "Downy Woodpecker": "Dryobates pubescens",
    "Bewick Wren": "Thryomanes bewickii",
    "Cactus Wren": "Campylorhynchus brunneicapillus",
    "Carolina Wren": "Thryothorus ludovicianus",
    "House Wren": "Troglodytes aedon",
    "Marsh Wren": "Cistothorus palustris",
    "Rock Wren": "Salpinctes obsoletus",
    "Winter Wren": "Troglodytes hiemalis",
    "Common Yellowthroat": "Geothlypis trichas"
}